riotgen/__init__.py
riotgen/application.py
riotgen/board.py
riotgen/common.py
riotgen/driver.py
riotgen/example.py
riotgen/main.py
riotgen/module.py
riotgen/pkg.py
riotgen/test.py
riotgen/utils.py
riotgen/data/licenses/AGPL3.txt
riotgen/data/licenses/Apache2.txt
riotgen/data/licenses/BSD.txt
riotgen/data/licenses/LGPL21.txt
riotgen/data/licenses/MIT.txt
riotgen/data/licenses/MPL2.txt
riotgen/templates/application/01-run.py.j2
riotgen/templates/application/Makefile.j2
riotgen/templates/application/README.md.j2
riotgen/templates/application/main.c.j2
riotgen/templates/board/Kconfig.j2
riotgen/templates/board/Makefile.dep.j2
riotgen/templates/board/Makefile.features.j2
riotgen/templates/board/Makefile.include.j2
riotgen/templates/board/Makefile.j2
riotgen/templates/board/board.h.j2
riotgen/templates/board/doc.md.j2
riotgen/templates/board/periph_conf.h.j2
riotgen/templates/common/header-headerfile.j2
riotgen/templates/common/header-licence.j2
riotgen/templates/driver/Kconfig.j2
riotgen/templates/driver/Makefile.dep.j2
riotgen/templates/driver/Makefile.include.j2
riotgen/templates/driver/Makefile.j2
riotgen/templates/driver/driver.c.j2
riotgen/templates/driver/driver.h.j2
riotgen/templates/driver/driver_constants.h.j2
riotgen/templates/driver/driver_netdev.c.j2
riotgen/templates/driver/driver_netdev.h.j2
riotgen/templates/driver/driver_params.h.j2
riotgen/templates/module/Makefile.j2
riotgen/templates/module/module.c.j2
riotgen/templates/module/module.h.j2
riotgen/templates/pkg/Kconfig.j2
riotgen/templates/pkg/Makefile.dep.j2
riotgen/templates/pkg/Makefile.include.j2
riotgen/templates/pkg/Makefile.j2
riotgen/templates/pkg/doc.md.j2
riotgen/templates/pkg/pkg.mk.j2
riotgen/tests/test_common.py
riotgen/tests/test_main.py
riotgen/tests/test_utils.py
riotgen/tests/test_data/test/01-run.py
riotgen-0.13.0.dist-info/licenses/COPYING
riotgen-0.13.0.dist-info/METADATA
riotgen-0.13.0.dist-info/WHEEL
riotgen-0.13.0.dist-info/entry_points.txt
riotgen-0.13.0.dist-info/top_level.txt
riotgen-0.13.0.dist-info/RECORD
