Metadata-Version: 2.4
Name: riotgen
Version: 0.13.0
Summary: riotgen: generator for RIOT source code.
Author-email: Alexandre Abadie <alexandre.abadie@inria.fr>
License-Expression: BSD-3-Clause
Project-URL: Homepage, https://github.com/aabadie/riot-generator
Project-URL: Bug Tracker, https://github.com/aaabadie/riot-generator/issues
Classifier: Programming Language :: Python :: 3
Classifier: Operating System :: MacOS
Classifier: Operating System :: POSIX :: Linux
Classifier: Operating System :: Microsoft :: Windows
Requires-Python: >=3.9
License-File: COPYING
Requires-Dist: rich-click>=1.8.6
Requires-Dist: jinja2>=3.0.2
Requires-Dist: pyyaml>=6.0
Dynamic: license-file
